tsg_export_cli/ProgramArgParser.py
tsg_export_cli/TSGImageReader.py
tsg_export_cli/TSGInterface.py
tsg_export_cli/TSGReader.py
tsg_export_cli/__init__.py
tsg_export_cli-0.0.2.dist-info/METADATA
tsg_export_cli-0.0.2.dist-info/WHEEL
tsg_export_cli-0.0.2.dist-info/entry_points.txt
tsg_export_cli-0.0.2.dist-info/licenses/LICENSE
tsg_export_cli-0.0.2.dist-info/RECORD
